{"success":true,"result":{"include_total":true,"resource_id":"27d2edc9-890e-4a42-bcae-6ba78dd3c331","fields":[{"type":"int","id":"_id"},{"type":"text","id":"rd_name"},{"type":"text","id":"rd_begin"},{"type":"text","id":"rd_end"},{"type":"int4","id":"rd_count"},{"type":"text","id":"use_cnt"},{"type":"text","id":"last_time"},{"type":"text","id":"tp_name"},{"type":"text","id":"hashCode"}],"records_format":"objects","records":[{"_id":1,"rd_name":"國強一街","rd_begin":"龍安街","rd_end":"益壽八街","rd_count":44,"use_cnt":"3","last_time":"2020/4/10 下午 07:57:00","tp_name":" 平日半小時計費,平日大車費率:10,平日小車費率:10,平日收費時段:08:00~18:00,假日半小時計費,假日大車費率:0,假日小車費率:0,假日收費時段:08:00~18:00","hashCode":"107430911"},{"_id":2,"rd_name":"民光東路","rd_begin":"春日路","rd_end":"大有路","rd_count":64,"use_cnt":"9","last_time":"2020/4/10 下午 07:57:00","tp_name":" 平日半小時計費,平日大車費率:10,平日小車費率:10,平日收費時段:08:00~18:00,假日半小時計費,假日大車費率:10,假日小車費率:10,假日收費時段:08:00~18:00","hashCode":"1895684370"},{"_id":3,"rd_name":"天祥七街","rd_begin":"新埔十街","rd_end":"經國路","rd_count":26,"use_cnt":"11","last_time":"2020/4/10 下午 07:57:00","tp_name":" 平日半小時計費,平日大車費率:10,平日小車費率:10,平日收費時段:08:00~18:00,假日半小時計費,假日大車費率:0,假日小車費率:0,假日收費時段:08:00~18:00","hashCode":"1849749621"},{"_id":4,"rd_name":"新埔十街","rd_begin":"莊敬路一段","rd_end":"天祥七街","rd_count":16,"use_cnt":"2","last_time":"2020/4/10 下午 07:57:00","tp_name":" 平日半小時計費,平日大車費率:10,平日小車費率:10,平日收費時段:08:00~18:00,假日半小時計費,假日大車費率:0,假日小車費率:0,假日收費時段:08:00~18:00","hashCode":"409163447"},{"_id":5,"rd_name":"德華街2","rd_begin":"國強一街","rd_end":"國際路二段","rd_count":36,"use_cnt":"2","last_time":"2020/4/10 下午 07:57:00","tp_name":" 平日半小時計費,平日大車費率:10,平日小車費率:10,平日收費時段:08:00~18:00,假日半小時計費,假日大車費率:0,假日小車費率:0,假日收費時段:08:00~18:00","hashCode":"614958847"},{"_id":6,"rd_name":"莊敬路二段","rd_begin":"寶慶路","rd_end":"富國路","rd_count":77,"use_cnt":"9","last_time":"2020/4/10 下午 07:57:00","tp_name":" 平日半小時計費,平日大車費率:10,平日小車費率:10,平日收費時段:08:00~18:00,假日半小時計費,假日大車費率:0,假日小車費率:0,10,0,假日收費時段:08:00~18:00","hashCode":"982318640"},{"_id":7,"rd_name":"莊一街","rd_begin":"中正路","rd_end":"敬三街","rd_count":17,"use_cnt":"2","last_time":"2020/4/10 下午 07:57:00","tp_name":" 平日半小時計費,平日大車費率:10,平日小車費率:10,平日收費時段:08:00~18:00,假日半小時計費,假日大車費率:0,假日小車費率:0,假日收費時段:08:00~18:00","hashCode":"1395024460"},{"_id":8,"rd_name":"莊二街","rd_begin":"同安街","rd_end":"敬三街","rd_count":33,"use_cnt":"15","last_time":"2020/4/10 下午 07:57:00","tp_name":" 平日半小時計費,平日大車費率:10,平日小車費率:10,平日收費時段:08:00~18:00,假日半小時計費,假日大車費率:0,假日小車費率:0,假日收費時段:08:00~18:00","hashCode":"1366446193"},{"_id":9,"rd_name":"公六街","rd_begin":"三民路二段","rd_end":"新生路","rd_count":11,"use_cnt":"11","last_time":"2020/4/10 下午 08:45:00","tp_name":" 平日半小時計費,平日大車費率:15,平日小車費率:15,平日收費時段:07:00~20:00,假日半小時計費,假日大車費率:15,假日小車費率:15,假日收費時段:07:00~20:00","hashCode":"1241162974"},{"_id":10,"rd_name":"巨蛋園區-第三停車場","rd_begin":"德育街","rd_end":"","rd_count":29,"use_cnt":"1","last_time":"2020/4/10 下午 08:45:00","tp_name":" 平日半小時計費,平日大車費率:10,平日小車費率:10,平日收費時段:08:00~20:00,假日半小時計費,假日大車費率:10,假日小車費率:10,假日收費時段:08:00~20:00","hashCode":"349879983"},{"_id":11,"rd_name":"巨蛋園區-第四停車場","rd_begin":"德育街","rd_end":"","rd_count":29,"use_cnt":"3","last_time":"2020/4/10 下午 08:45:00","tp_name":" 平日半小時計費,平日大車費率:10,平日小車費率:10,平日收費時段:08:00~20:00,假日半小時計費,假日大車費率:10,假日小車費率:10,假日收費時段:08:00~20:00","hashCode":"1955502714"},{"_id":12,"rd_name":"巨蛋園區-第五停車場","rd_begin":"德育街","rd_end":"","rd_count":18,"use_cnt":"5","last_time":"2020/4/10 下午 08:45:00","tp_name":" 平日半小時計費,平日大車費率:10,平日小車費率:10,平日收費時段:08:00~20:00,假日半小時計費,假日大車費率:10,假日小車費率:10,假日收費時段:08:00~20:00","hashCode":"926723394"},{"_id":13,"rd_name":"巨蛋園區-第六停車場","rd_begin":"德育街","rd_end":"","rd_count":12,"use_cnt":"3","last_time":"2020/2/25 下午 06:58:00","tp_name":" 平日半小時計費,平日大車費率:10,平日小車費率:10,平日收費時段:08:00~20:00,假日半小時計費,假日大車費率:10,假日小車費率:10,假日收費時段:08:00~20:00","hashCode":"737948463"},{"_id":14,"rd_name":"大林路","rd_begin":"桃鶯路","rd_end":"昆明路","rd_count":46,"use_cnt":"29","last_time":"2020/4/10 下午 08:45:00","tp_name":" 平日半小時計費,平日大車費率:10,平日小車費率:15,平日收費時段:07:00~20:00,假日半小時計費,假日大車費率:0,假日小車費率:15,假日收費時段:07:00~20:00","hashCode":"1788006201"},{"_id":15,"rd_name":"建國路","rd_begin":"桃鶯路","rd_end":"昆明路","rd_count":45,"use_cnt":"9","last_time":"2020/4/10 下午 07:57:00","tp_name":" 平日半小時計費,平日大車費率:10,平日小車費率:10,平日收費時段:08:00~18:00,假日無計費,假日大車費率:0,假日小車費率:0,假日收費時段:00:00~00:00","hashCode":"1783612763"},{"_id":16,"rd_name":"福吉一街","rd_begin":"昆明路","rd_end":"延平路","rd_count":16,"use_cnt":"1","last_time":"2020/4/10 下午 07:57:00","tp_name":" 平日半小時計費,平日大車費率:10,平日小車費率:10,平日收費時段:08:00~18:00,假日無計費,假日大車費率:0,假日小車費率:0,假日收費時段:00:00~00:00","hashCode":"944448493"},{"_id":17,"rd_name":"福吉二街","rd_begin":"福吉一街","rd_end":"福吉三街","rd_count":14,"use_cnt":"3","last_time":"2020/4/10 下午 07:57:00","tp_name":" 平日半小時計費,平日大車費率:10,平日小車費率:10,平日收費時段:08:00~18:00,假日無計費,假日大車費率:0,假日小車費率:0,假日收費時段:00:00~00:00","hashCode":"1919158912"},{"_id":18,"rd_name":"福吉三街","rd_begin":"大林路","rd_end":"建國路","rd_count":28,"use_cnt":"2","last_time":"2020/4/10 下午 07:57:00","tp_name":" 平日半小時計費,平日大車費率:10,平日小車費率:10,平日收費時段:08:00~18:00,假日無計費,假日大車費率:00,假日小車費率:0,假日收費時段:08:00~18:00","hashCode":"250865906"},{"_id":19,"rd_name":"桃鶯路","rd_begin":"大林路","rd_end":"建成街","rd_count":15,"use_cnt":"15","last_time":"2020/4/10 下午 06:54:00","tp_name":" 平日半小時計費,平日大車費率:10,平日小車費率:10,平日收費時段:08:00~18:00,假日無計費,假日大車費率:00,假日小車費率:0,假日收費時段:08:00~18:00","hashCode":"444764522"},{"_id":20,"rd_name":"昆明路","rd_begin":"大林路","rd_end":"建國路","rd_count":25,"use_cnt":"4","last_time":"2020/4/10 下午 06:54:00","tp_name":" 平日半小時計費,平日大車費率:10,平日小車費率:10,平日收費時段:08:00~18:00,假日無計費,假日大車費率:0,假日小車費率:0,假日收費時段:00:00~00:00","hashCode":"2075626908"},{"_id":21,"rd_name":"民族路橋橋下空間","rd_begin":"建國路","rd_end":"介壽路6巷","rd_count":61,"use_cnt":"2","last_time":"2020/4/10 下午 06:54:00","tp_name":" 平日半小時計費,平日大車費率:10,平日小車費率:10,平日收費時段:08:00~18:00,假日無計費,假日大車費率:0,假日小車費率:0,假日收費時段:00:00~00:00","hashCode":"701872224"},{"_id":22,"rd_name":"大興路","rd_begin":"大有路","rd_end":"春日路","rd_count":17,"use_cnt":"6","last_time":"2020/4/10 下午 07:57:00","tp_name":" 平日半小時計費,平日大車費率:10,平日小車費率:10,平日收費時段:08:00~18:00,假日半小時計費,假日大車費率:10,假日小車費率:10,假日收費時段:00:00~00:00","hashCode":"955281872"},{"_id":23,"rd_name":"江南二街","rd_begin":"龍安街14巷","rd_end":"茄苳溪旁","rd_count":6,"use_cnt":"6","last_time":"2020/4/10 下午 06:54:00","tp_name":" 平日半小時計費,平日大車費率:10,平日小車費率:10,平日收費時段:08:00~18:00,假日半小時計費,假日大車費率:10,假日小車費率:10,假日收費時段:00:00~00:00","hashCode":"922201701"},{"_id":24,"rd_name":"信光路","rd_begin":"正康二街","rd_end":"正康三街","rd_count":14,"use_cnt":"2","last_time":"2020/4/10 下午 07:57:00","tp_name":" 平日半小時計費,平日大車費率:10,平日小車費率:10,平日收費時段:08:00~18:00,假日半小時計費,假日大車費率:10,假日小車費率:10,假日收費時段:00:00~00:00","hashCode":"1911230026"},{"_id":25,"rd_name":"南通公園","rd_begin":"南通路","rd_end":"五福三街","rd_count":82,"use_cnt":"12","last_time":"2020/4/10 下午 07:57:00","tp_name":" 平日半小時計費,平日大車費率:10,平日小車費率:10,平日收費時段:08:00~18:00,假日半小時計費,假日大車費率:10,假日小車費率:10,假日收費時段:00:00~00:00","hashCode":"1970908847"},{"_id":26,"rd_name":"正康二街","rd_begin":"信光路","rd_end":"美光街","rd_count":2,"use_cnt":"1","last_time":"2020/4/10 下午 06:54:00","tp_name":" 平日半小時計費,平日大車費率:10,平日小車費率:10,平日收費時段:08:00~18:00,假日半小時計費,假日大車費率:10,假日小車費率:10,假日收費時段:00:00~00:00","hashCode":"1312571169"},{"_id":27,"rd_name":"江南四街","rd_begin":"上海路","rd_end":"茄苳溪旁","rd_count":19,"use_cnt":"12","last_time":"2020/4/10 下午 06:54:00","tp_name":" 平日半小時計費,平日大車費率:10,平日小車費率:10,平日收費時段:08:00~18:00,假日半小時計費,假日大車費率:10,假日小車費率:10,假日收費時段:00:00~00:00","hashCode":"1169368069"},{"_id":28,"rd_name":"大林路(機車)","rd_begin":"桃鶯路","rd_end":"昆明路","rd_count":160,"use_cnt":"1","last_time":"2020/4/10 上午 10:59:00","tp_name":" 平日計次計費,平日大車費率:00,平日小車費率:00,平日收費時段:08:00~18:00,假日計次計費,假日大車費率:00,假日小車費率:00,假日收費時段:07:00~20:00","hashCode":"1812200359"},{"_id":29,"rd_name":"中山東路126巷","rd_begin":"中山東路","rd_end":"成功路二段","rd_count":31,"use_cnt":"3","last_time":"2020/4/10 下午 07:57:00","tp_name":" 平日半小時計費,平日大車費率:10,平日小車費率:10,平日收費時段:08:00~18:00,假日無計費,假日大車費率:00,假日小車費率:0,假日收費時段:00:00~00:00","hashCode":"1412906078"},{"_id":30,"rd_name":"介壽路","rd_begin":"保羅街","rd_end":"介新街","rd_count":56,"use_cnt":"5","last_time":"2020/4/10 下午 07:57:00","tp_name":" 平日半小時計費,平日大車費率:10,平日小車費率:10,平日收費時段:08:00~18:00,假日無計費,假日大車費率:00,假日小車費率:0,假日收費時段:00:00~00:00","hashCode":"2078135502"},{"_id":31,"rd_name":"南豐三街","rd_begin":"介壽路","rd_end":"南豐街","rd_count":17,"use_cnt":"6","last_time":"2020/4/10 下午 07:57:00","tp_name":" 平日半小時計費,平日大車費率:5,平日小車費率:10,平日收費時段:08:00~18:00,假日無計費,假日大車費率:0,假日小車費率:0,假日收費時段:00:00~00:00","hashCode":"655512764"},{"_id":32,"rd_name":"建新街","rd_begin":"保羅街","rd_end":"長沙街","rd_count":35,"use_cnt":"12","last_time":"2020/4/10 下午 07:57:00","tp_name":" 平日半小時計費,平日大車費率:05,平日小車費率:10,平日收費時段:08:00~18:00,假日無計費,假日大車費率:0,假日小車費率:0,假日收費時段:00:00~00:00","hashCode":"1413438778"},{"_id":33,"rd_name":"長沙街","rd_begin":"介壽路","rd_end":"建新街","rd_count":31,"use_cnt":"11","last_time":"2020/4/10 下午 07:57:00","tp_name":" 平日半小時計費,平日大車費率:05,平日小車費率:10,平日收費時段:08:00~18:00,假日無計費,假日大車費率:0,假日小車費率:0,假日收費時段:00:00~00:00","hashCode":"965168687"},{"_id":34,"rd_name":"保羅街","rd_begin":"介壽路","rd_end":"建新街","rd_count":25,"use_cnt":"7","last_time":"2020/4/10 下午 07:57:00","tp_name":" 平日半小時計費,平日大車費率:05,平日小車費率:10,平日收費時段:08:00~18:00,假日無計費,假日大車費率:0,假日小車費率:0,假日收費時段:00:00~00:00","hashCode":"753505909"},{"_id":35,"rd_name":"陽明十二街","rd_begin":"長沙街","rd_end":"介新街","rd_count":25,"use_cnt":"6","last_time":"2020/4/10 下午 07:57:00","tp_name":" 平日半小時計費,平日大車費率:05,平日小車費率:10,平日收費時段:08:00~18:00,假日無計費,假日大車費率:0,假日小車費率:0,假日收費時段:00:00~00:00","hashCode":"426479840"},{"_id":36,"rd_name":"陽明五街","rd_begin":"長沙街","rd_end":"介新街","rd_count":25,"use_cnt":"5","last_time":"2020/4/10 下午 07:57:00","tp_name":" 平日半小時計費,平日大車費率:05,平日小車費率:10,平日收費時段:08:00~18:00,假日無計費,假日大車費率:0,假日小車費率:0,假日收費時段:00:00~00:00","hashCode":"924043386"},{"_id":37,"rd_name":"介新街","rd_begin":"介壽路","rd_end":"陽明五街","rd_count":22,"use_cnt":"4","last_time":"2020/4/10 下午 07:57:00","tp_name":" 平日半小時計費,平日大車費率:05,平日小車費率:10,平日收費時段:08:00~18:00,假日無計費,假日大車費率:0,假日小車費率:0,假日收費時段:00:00~00:00","hashCode":"887496321"},{"_id":38,"rd_name":"正康三街115巷","rd_begin":"大連一街","rd_end":"正康三街","rd_count":3,"use_cnt":"1","last_time":"2020/4/10 下午 07:57:00","tp_name":" 平日半小時計費,平日大車費率:10,平日小車費率:10,平日收費時段:08:00~18:00,假日無計費,假日大車費率:00,假日小車費率:0,假日收費時段:00:00~00:00","hashCode":"1423731798"},{"_id":39,"rd_name":"復興路","rd_begin":"中山路","rd_end":"中央東路","rd_count":17,"use_cnt":"16","last_time":"2020/4/10 下午 08:45:00","tp_name":" 平日半小時計費,平日大車費率:15,平日小車費率:15,平日收費時段:07:00~20:00,假日半小時計費,假日大車費率:15,假日小車費率:15,假日收費時段:07:00~20:00","hashCode":"292883133"},{"_id":40,"rd_name":"中山路","rd_begin":"義民路","rd_end":"和平路","rd_count":50,"use_cnt":"36","last_time":"2020/4/10 下午 08:45:00","tp_name":" 平日半小時計費,平日大車費率:15,平日小車費率:15,平日收費時段:07:00~20:00,假日半小時計費,假日大車費率:15,假日小車費率:15,假日收費時段:07:00~20:00","hashCode":"940331249"},{"_id":41,"rd_name":"中正路","rd_begin":"火車站","rd_end":"明德路","rd_count":32,"use_cnt":"20","last_time":"2020/4/10 下午 08:45:00","tp_name":" 平日半小時計費,平日大車費率:15,平日小車費率:15,平日收費時段:07:00~20:00,假日半小時計費,假日大車費率:15,假日小車費率:15,假日收費時段:07:00~20:00","hashCode":"1016742759"},{"_id":42,"rd_name":"中央西路","rd_begin":"延平路","rd_end":"三光路","rd_count":149,"use_cnt":"133","last_time":"2020/4/10 下午 08:45:00","tp_name":" 平日半小時計費,平日大車費率:15,平日小車費率:15,平日收費時段:07:00~20:00,假日半小時計費,假日大車費率:15,假日小車費率:15,假日收費時段:07:00~20:00","hashCode":"185804414"},{"_id":43,"rd_name":"中豐路","rd_begin":"中央西路","rd_end":"環北路","rd_count":29,"use_cnt":"26","last_time":"2020/4/10 下午 08:45:00","tp_name":" 平日半小時計費,平日大車費率:15,平日小車費率:15,平日收費時段:07:00~20:00,假日半小時計費,假日大車費率:15,假日小車費率:15,假日收費時段:07:00~20:00","hashCode":"839574851"},{"_id":44,"rd_name":"中美路","rd_begin":"延平路","rd_end":"新生路","rd_count":5,"use_cnt":"5","last_time":"2020/4/10 下午 08:45:00","tp_name":" 平日半小時計費,平日大車費率:15,平日小車費率:15,平日收費時段:07:00~20:00,假日半小時計費,假日大車費率:15,假日小車費率:15,假日收費時段:07:00~20:00","hashCode":"1750839339"},{"_id":45,"rd_name":"新生路","rd_begin":"環北路","rd_end":"中央西路","rd_count":45,"use_cnt":"35","last_time":"2020/4/10 下午 08:45:00","tp_name":" 平日半小時計費,平日大車費率:15,平日小車費率:15,平日收費時段:07:00~20:00,假日半小時計費,假日大車費率:15,假日小車費率:15,假日收費時段:07:00~20:00","hashCode":"104093500"},{"_id":46,"rd_name":"元化路","rd_begin":"長江路","rd_end":"新生路","rd_count":40,"use_cnt":"32","last_time":"2020/4/10 下午 08:45:00","tp_name":" 平日半小時計費,平日大車費率:15,平日小車費率:15,平日收費時段:07:00~20:00,假日半小時計費,假日大車費率:15,假日小車費率:15,假日收費時段:07:00~20:00","hashCode":"344367442"},{"_id":47,"rd_name":"九和二街","rd_begin":"慈惠三街","rd_end":"新生路","rd_count":23,"use_cnt":"23","last_time":"2020/4/10 下午 08:45:00","tp_name":" 平日半小時計費,平日大車費率:15,平日小車費率:15,平日收費時段:07:00~20:00,假日半小時計費,假日大車費率:15,假日小車費率:15,假日收費時段:07:00~20:00","hashCode":"1908633212"},{"_id":48,"rd_name":"九和三街","rd_begin":"慈惠三街","rd_end":"新生路","rd_count":19,"use_cnt":"17","last_time":"2020/4/10 下午 08:45:00","tp_name":" 平日半小時計費,平日大車費率:15,平日小車費率:15,平日收費時段:07:00~20:00,假日半小時計費,假日大車費率:15,假日小車費率:15,假日收費時段:07:00~20:00","hashCode":"1143751303"},{"_id":49,"rd_name":"九和五街","rd_begin":"慈惠三街","rd_end":"新生路","rd_count":14,"use_cnt":"14","last_time":"2020/4/10 下午 08:45:00","tp_name":" 平日半小時計費,平日大車費率:15,平日小車費率:15,平日收費時段:07:00~20:00,假日半小時計費,假日大車費率:15,假日小車費率:15,假日收費時段:07:00~20:00","hashCode":"1610965129"},{"_id":50,"rd_name":"九和六街","rd_begin":"慈惠三街","rd_end":"新生路","rd_count":14,"use_cnt":"13","last_time":"2020/4/10 下午 08:45:00","tp_name":" 平日半小時計費,平日大車費率:15,平日小車費率:15,平日收費時段:07:00~20:00,假日半小時計費,假日大車費率:15,假日小車費率:15,假日收費時段:07:00~20:00","hashCode":"1093194218"},{"_id":51,"rd_name":"六和路","rd_begin":"環北路","rd_end":"元化路","rd_count":32,"use_cnt":"26","last_time":"2020/4/10 下午 08:45:00","tp_name":" 平日半小時計費,平日大車費率:15,平日小車費率:15,平日收費時段:07:00~20:00,假日半小時計費,假日大車費率:15,假日小車費率:15,假日收費時段:07:00~20:00","hashCode":"728954685"},{"_id":52,"rd_name":"慈惠三街","rd_begin":"環北路","rd_end":"元化路","rd_count":36,"use_cnt":"33","last_time":"2020/4/10 下午 08:45:00","tp_name":" 平日半小時計費,平日大車費率:15,平日小車費率:15,平日收費時段:07:00~20:00,假日半小時計費,假日大車費率:15,假日小車費率:15,假日收費時段:07:00~20:00","hashCode":"233615534"},{"_id":53,"rd_name":"延平路一含266巷及七和一街","rd_begin":"元化路","rd_end":"康樂路","rd_count":130,"use_cnt":"97","last_time":"2020/4/10 下午 08:45:00","tp_name":" 平日半小時計費,平日大車費率:15,平日小車費率:15,平日收費時段:07:00~20:00,假日半小時計費,假日大車費率:15,假日小車費率:15,假日收費時段:07:00~20:00","hashCode":"1185319090"},{"_id":54,"rd_name":"大同路","rd_begin":"中正路","rd_end":"中央西路","rd_count":7,"use_cnt":"6","last_time":"2020/4/10 下午 08:45:00","tp_name":" 平日半小時計費,平日大車費率:15,平日小車費率:15,平日收費時段:07:00~20:00,假日半小時計費,假日大車費率:15,假日小車費率:15,假日收費時段:07:00~20:00","hashCode":"1099347469"},{"_id":55,"rd_name":"民族路","rd_begin":"明德路","rd_end":"中壢交流道","rd_count":113,"use_cnt":"41","last_time":"2020/4/10 下午 08:45:00","tp_name":" 平日半小時計費,平日大車費率:15,平日小車費率:15,平日收費時段:07:00~20:00,假日無計費,假日大車費率:00,假日小車費率:00,假日收費時段:07:00~20:00","hashCode":"2112973343"},{"_id":56,"rd_name":"三光路","rd_begin":"中正路","rd_end":"民權路","rd_count":99,"use_cnt":"32","last_time":"2020/4/10 下午 07:57:00","tp_name":" 平日半小時計費,平日大車費率:10,平日小車費率:10,平日收費時段:08:00~18:00,假日無計費,假日大車費率:00,假日小車費率:00,假日收費時段:08:00~18:00","hashCode":"359718095"},{"_id":57,"rd_name":"環北路","rd_begin":"延平路","rd_end":"民權路","rd_count":103,"use_cnt":"8","last_time":"2020/4/10 下午 07:57:00","tp_name":" 平日半小時計費,平日大車費率:10,平日小車費率:10,平日收費時段:08:00~18:00,假日無計費,假日大車費率:00,假日小車費率:00,假日收費時段:08:00~18:00","hashCode":"1734419915"},{"_id":58,"rd_name":"環西路","rd_begin":"民權路","rd_end":"民族路","rd_count":157,"use_cnt":"51","last_time":"2020/4/10 下午 07:57:00","tp_name":" 平日半小時計費,平日大車費率:10,平日小車費率:10,平日收費時段:08:00~18:00,假日無計費,假日大車費率:00,假日小車費率:00,假日收費時段:08:00~18:00","hashCode":"321114612"},{"_id":59,"rd_name":"明德南路","rd_begin":"義民路","rd_end":"中正路","rd_count":31,"use_cnt":"3","last_time":"2020/4/10 下午 07:57:00","tp_name":" 平日半小時計費,平日大車費率:10,平日小車費率:10,平日收費時段:08:00~18:00,假日半小時計費,假日大車費率:10,假日小車費率:10,假日收費時段:08:00~18:00","hashCode":"1710551069"},{"_id":60,"rd_name":"新明路","rd_begin":"民族路","rd_end":"中央西路","rd_count":16,"use_cnt":"4","last_time":"2020/4/10 下午 07:57:00","tp_name":" 平日半小時計費,平日大車費率:10,平日小車費率:10,平日收費時段:08:00~18:00,假日半小時計費,假日大車費率:10,假日小車費率:10,假日收費時段:08:00~18:00","hashCode":"1995562696"},{"_id":61,"rd_name":"環中東路","rd_begin":"強國路","rd_end":"永福路","rd_count":55,"use_cnt":"10","last_time":"2020/4/10 下午 07:57:00","tp_name":" 平日半小時計費,平日大車費率:10,平日小車費率:10,平日收費時段:08:00~18:00,假日半小時計費,假日大車費率:10,假日小車費率:10,假日收費時段:08:00~18:00","hashCode":"407954080"},{"_id":62,"rd_name":"溪洲街","rd_begin":"普義路","rd_end":"中山路","rd_count":26,"use_cnt":"1","last_time":"2020/4/10 下午 07:57:00","tp_name":" 平日半小時計費,平日大車費率:10,平日小車費率:10,平日收費時段:08:00~18:00,假日無計費,假日大車費率:00,假日小車費率:00,假日收費時段:08:00~18:00","hashCode":"359738415"},{"_id":63,"rd_name":"文中路三","rd_begin":"龍壽街一段","rd_end":"吉林北路","rd_count":236,"use_cnt":"4","last_time":"2020/4/10 下午 07:57:00","tp_name":" 平日半小時計費,平日大車費率:10,平日小車費率:10,平日收費時段:08:00~18:00,假日無計費,假日大車費率:0,假日小車費率:0,假日收費時段:08:00~18:00","hashCode":"1464287876"},{"_id":64,"rd_name":"中榮路","rd_begin":"康樂路","rd_end":"中正路","rd_count":10,"use_cnt":"10","last_time":"2020/4/10 下午 08:45:00","tp_name":" 平日半小時計費,平日大車費率:15,平日小車費率:15,平日收費時段:07:00~20:00,假日半小時計費,假日大車費率:15,假日小車費率:15,假日收費時段:07:00~20:00","hashCode":"800641338"},{"_id":65,"rd_name":"青埔路一、二段","rd_begin":"領航北路三段","rd_end":"領航南路二段","rd_count":120,"use_cnt":"2","last_time":"2020/4/10 下午 07:57:00","tp_name":" 平日半小時計費,平日大車費率:10,平日小車費率:10,平日收費時段:08:00~18:00,假日半小時計費,假日大車費率:10,假日小車費率:10,假日收費時段:08:00~18:00","hashCode":"820142991"},{"_id":66,"rd_name":"青心路","rd_begin":"高鐵北路一段","rd_end":"領航南路三段","rd_count":90,"use_cnt":"4","last_time":"2020/4/10 下午 07:57:00","tp_name":" 平日半小時計費,平日大車費率:10,平日小車費率:10,平日收費時段:08:00~18:00,假日半小時計費,假日大車費率:10,假日小車費率:10,假日收費時段:08:00~18:00","hashCode":"745419240"},{"_id":67,"rd_name":"青昇路","rd_begin":"領航北路三段","rd_end":"領航南路三段","rd_count":163,"use_cnt":"12","last_time":"2020/4/10 下午 07:57:00","tp_name":" 平日半小時計費,平日大車費率:10,平日小車費率:10,平日收費時段:08:00~18:00,假日半小時計費,假日大車費率:10,假日小車費率:10,假日收費時段:08:00~18:00","hashCode":"1095763331"},{"_id":68,"rd_name":"新生路一","rd_begin":"環北路","rd_end":"新生路509巷","rd_count":15,"use_cnt":"11","last_time":"2020/4/10 下午 06:54:00","tp_name":" 平日半小時計費,平日大車費率:10,平日小車費率:10,平日收費時段:08:00~18:00,假日無計費,假日大車費率:00,假日小車費率:0,假日收費時段:00:00~00:00","hashCode":"671628690"},{"_id":69,"rd_name":"忠義路","rd_begin":"中華路二段","rd_end":"忠信路","rd_count":51,"use_cnt":"13","last_time":"2020/4/10 下午 07:57:00","tp_name":" 平日半小時計費,平日大車費率:10,平日小車費率:10,平日收費時段:08:00~18:00,假日半小時計費,假日大車費率:10,假日小車費率:10,假日收費時段:08:00~18:00","hashCode":"190176519"},{"_id":70,"rd_name":"文化二路","rd_begin":"中華路一段","rd_end":"元生三街","rd_count":88,"use_cnt":"1","last_time":"2020/4/10 下午 07:57:00","tp_name":" 平日半小時計費,平日大車費率:10,平日小車費率:10,平日收費時段:08:00~18:00,假日無計費,假日大車費率:0,假日小車費率:0,假日收費時段:00:00~00:00","hashCode":"1458134260"},{"_id":71,"rd_name":"高鐵南路一段","rd_begin":"青埔路二段","rd_end":"領航南路一段","rd_count":133,"use_cnt":"12","last_time":"2020/4/10 下午 07:57:00","tp_name":" 平日半小時計費,平日大車費率:10,平日小車費率:10,平日收費時段:08:00~18:00,假日半小時計費,假日大車費率:10,假日小車費率:10,假日收費時段:08:00~18:00","hashCode":"391391159"},{"_id":72,"rd_name":"忠孝路","rd_begin":"中華路一段","rd_end":"興農路","rd_count":3,"use_cnt":"3","last_time":"2020/4/10 下午 06:54:00","tp_name":" 平日半小時計費,平日大車費率:10,平日小車費率:10,平日收費時段:08:00~18:00,假日無計費,假日大車費率:0,假日小車費率:0,假日收費時段:00:00~00:00","hashCode":"2128178274"},{"_id":73,"rd_name":"中豐路2","rd_begin":"中央西路二段","rd_end":"中山路","rd_count":15,"use_cnt":"14","last_time":"2020/4/10 下午 08:45:00","tp_name":" 平日半小時計費,平日大車費率:15,平日小車費率:15,平日收費時段:07:00~20:00,假日半小時計費,假日大車費率:15,假日小車費率:15,假日收費時段:07:00~20:00","hashCode":"1531001691"},{"_id":74,"rd_name":"復興一路1","rd_begin":"文化一路","rd_end":"文化三路","rd_count":28,"use_cnt":"1","last_time":"2019/12/17 下午 06:56:00","tp_name":" 平日半小時計費,平日大車費率:15,平日小車費率:15,平日收費時段:07:00~20:00,假日半小時計費,假日大車費率:15,假日小車費率:15,假日收費時段:07:00~20:00","hashCode":"1205060155"},{"_id":75,"rd_name":"復興一路2","rd_begin":"文化三路","rd_end":"忠義路二段","rd_count":100,"use_cnt":"10","last_time":"2020/2/5 下午 02:59:00","tp_name":" 平日半小時計費,平日大車費率:15,平日小車費率:15,平日收費時段:07:00~20:00,假日半小時計費,假日大車費率:15,假日小車費率:15,假日收費時段:07:00~20:00","hashCode":"1896623337"},{"_id":76,"rd_name":"萬壽路二段1","rd_begin":"興中街","rd_end":"大同路","rd_count":59,"use_cnt":"40","last_time":"2020/4/10 下午 08:45:00","tp_name":" 平日半小時計費,平日大車費率:15,平日小車費率:15,平日收費時段:07:00~20:00,假日半小時計費,假日大車費率:15,假日小車費率:15,假日收費時段:07:00~20:00","hashCode":"1141105878"},{"_id":77,"rd_name":"萬壽路二段3","rd_begin":"大同路","rd_end":"振興路","rd_count":62,"use_cnt":"24","last_time":"2020/4/10 下午 08:45:00","tp_name":" 平日半小時計費,平日大車費率:15,平日小車費率:15,平日收費時段:07:00~20:00,假日半小時計費,假日大車費率:15,假日小車費率:15,假日收費時段:07:00~20:00","hashCode":"382371054"},{"_id":78,"rd_name":"復興三路","rd_begin":"文化一路","rd_end":"文化三路","rd_count":90,"use_cnt":"3","last_time":"2020/4/10 下午 07:57:00","tp_name":" 平日半小時計費,平日大車費率:10,平日小車費率:10,平日收費時段:08:00~18:00,假日半小時計費,假日大車費率:10,假日小車費率:10,假日收費時段:08:00~18:00","hashCode":"1330728470"},{"_id":79,"rd_name":"文化二路1","rd_begin":"文二一街","rd_end":"公園路","rd_count":58,"use_cnt":"1","last_time":"2020/4/10 下午 07:57:00","tp_name":" 平日半小時計費,平日大車費率:10,平日小車費率:10,平日收費時段:08:00~18:00,假日半小時計費,假日大車費率:10,假日小車費率:10,假日收費時段:08:00~18:00","hashCode":"1596610673"},{"_id":80,"rd_name":"文化二路2","rd_begin":"龜山一路","rd_end":"文二一街","rd_count":48,"use_cnt":"2","last_time":"2020/4/10 下午 06:54:00","tp_name":" 平日半小時計費,平日大車費率:10,平日小車費率:10,平日收費時段:08:00~18:00,假日半小時計費,假日大車費率:10,假日小車費率:10,假日收費時段:08:00~18:00","hashCode":"81015318"},{"_id":81,"rd_name":"文化二路3","rd_begin":"公園路","rd_end":"復興三路","rd_count":72,"use_cnt":"4","last_time":"2020/4/10 下午 07:57:00","tp_name":" 平日半小時計費,平日大車費率:10,平日小車費率:10,平日收費時段:08:00~18:00,假日半小時計費,假日大車費率:10,假日小車費率:10,假日收費時段:08:00~18:00","hashCode":"1190865814"},{"_id":82,"rd_name":"文化三路1","rd_begin":"文二一街","rd_end":"公園路","rd_count":76,"use_cnt":"5","last_time":"2020/4/10 下午 06:54:00","tp_name":" 平日半小時計費,平日大車費率:10,平日小車費率:10,平日收費時段:08:00~18:00,假日半小時計費,假日大車費率:10,假日小車費率:10,假日收費時段:08:00~18:00","hashCode":"60812449"},{"_id":83,"rd_name":"文化三路2","rd_begin":"龜山一路","rd_end":"文二一街","rd_count":64,"use_cnt":"1","last_time":"2020/3/2 下午 06:56:00","tp_name":" 平日半小時計費,平日大車費率:10,平日小車費率:10,平日收費時段:08:00~18:00,假日半小時計費,假日大車費率:10,假日小車費率:10,假日收費時段:08:00~18:00","hashCode":"251381107"},{"_id":84,"rd_name":"文化三路3","rd_begin":"公園路","rd_end":"復興三路","rd_count":77,"use_cnt":"11","last_time":"2020/4/10 下午 06:54:00","tp_name":" 平日半小時計費,平日大車費率:10,平日小車費率:10,平日收費時段:08:00~18:00,假日半小時計費,假日大車費率:10,假日小車費率:10,假日收費時段:08:00~18:00","hashCode":"723124792"},{"_id":85,"rd_name":"文二一街","rd_begin":"文化二路","rd_end":"文化三路","rd_count":36,"use_cnt":"6","last_time":"2020/4/10 下午 07:57:00","tp_name":" 平日半小時計費,平日大車費率:10,平日小車費率:10,平日收費時段:08:00~18:00,假日半小時計費,假日大車費率:10,假日小車費率:10,假日收費時段:08:00~18:00","hashCode":"883043158"},{"_id":86,"rd_name":"文二三街","rd_begin":"文化三路37巷","rd_end":"文化二路34巷","rd_count":25,"use_cnt":"21","last_time":"2020/4/10 下午 06:54:00","tp_name":" 平日半小時計費,平日大車費率:10,平日小車費率:10,平日收費時段:08:00~18:00,假日半小時計費,假日大車費率:10,假日小車費率:10,假日收費時段:08:00~18:00","hashCode":"1210327943"},{"_id":87,"rd_name":"文興路","rd_begin":"公園路","rd_end":"文二一街","rd_count":102,"use_cnt":"1","last_time":"2020/4/10 下午 07:57:00","tp_name":" 平日半小時計費,平日大車費率:10,平日小車費率:10,平日收費時段:08:00~18:00,假日半小時計費,假日大車費率:10,假日小車費率:10,假日收費時段:08:00~18:00","hashCode":"405059501"},{"_id":88,"rd_name":"公園路","rd_begin":"文化二路","rd_end":"文化三路","rd_count":32,"use_cnt":"3","last_time":"2020/4/10 下午 07:57:00","tp_name":" 平日半小時計費,平日大車費率:10,平日小車費率:10,平日收費時段:08:00~18:00,假日半小時計費,假日大車費率:10,假日小車費率:10,假日收費時段:08:00~18:00","hashCode":"1666481491"},{"_id":89,"rd_name":"龜山一路","rd_begin":"文化一路","rd_end":"文化二路","rd_count":40,"use_cnt":"5","last_time":"2020/4/10 下午 07:57:00","tp_name":" 平日半小時計費,平日大車費率:10,平日小車費率:10,平日收費時段:08:00~18:00,假日半小時計費,假日大車費率:10,假日小車費率:10,假日收費時段:08:00~18:00","hashCode":"1174999796"},{"_id":90,"rd_name":"大同路","rd_begin":"萬壽路二段","rd_end":"德明路","rd_count":37,"use_cnt":"1","last_time":"2020/4/10 下午 07:57:00","tp_name":" 平日半小時計費,平日大車費率:10,平日小車費率:10,平日收費時段:08:00~18:00,假日半小時計費,假日大車費率:10,假日小車費率:10,假日收費時段:08:00~18:00","hashCode":"802695593"},{"_id":91,"rd_name":"德明路","rd_begin":"大同路","rd_end":"明德路77巷","rd_count":6,"use_cnt":"2","last_time":"2020/4/10 下午 07:57:00","tp_name":" 平日半小時計費,平日大車費率:10,平日小車費率:10,平日收費時段:08:00~18:00,假日半小時計費,假日大車費率:10,假日小車費率:10,假日收費時段:08:00~18:00","hashCode":"310143520"},{"_id":92,"rd_name":"自強東路","rd_begin":"萬壽路二段","rd_end":"大同路","rd_count":73,"use_cnt":"12","last_time":"2020/4/10 下午 07:57:00","tp_name":" 平日半小時計費,平日大車費率:10,平日小車費率:10,平日收費時段:08:00~18:00,假日半小時計費,假日大車費率:10,假日小車費率:10,假日收費時段:08:00~18:00","hashCode":"1375876057"},{"_id":93,"rd_name":"自強南路","rd_begin":"大同路","rd_end":"萬壽路二段","rd_count":107,"use_cnt":"16","last_time":"2020/4/10 下午 07:57:00","tp_name":" 平日半小時計費,平日大車費率:10,平日小車費率:10,平日收費時段:08:00~18:00,假日半小時計費,假日大車費率:10,假日小車費率:10,假日收費時段:08:00~18:00","hashCode":"1544685023"},{"_id":94,"rd_name":"復興二路","rd_begin":"文化二路","rd_end":"文化三路","rd_count":40,"use_cnt":"23","last_time":"2020/4/10 下午 06:54:00","tp_name":" 平日半小時計費,平日大車費率:10,平日小車費率:10,平日收費時段:08:00~18:00,假日半小時計費,假日大車費率:10,假日小車費率:10,假日收費時段:08:00~18:00","hashCode":"845806229"},{"_id":95,"rd_name":"湖邊路","rd_begin":"龜山一路","rd_end":"院前二路","rd_count":29,"use_cnt":"1","last_time":"2020/4/10 下午 08:45:00","tp_name":" 平日半小時計費,平日大車費率:15,平日小車費率:15,平日收費時段:07:00~20:00,假日半小時計費,假日大車費率:15,假日小車費率:15,假日收費時段:07:00~20:00","hashCode":"1135979410"},{"_id":96,"rd_name":"同心一、二路","rd_begin":"長壽路","rd_end":"長壽路","rd_count":90,"use_cnt":"11","last_time":"2020/4/10 下午 07:57:00","tp_name":" 平日半小時計費,平日大車費率:10,平日小車費率:10,平日收費時段:08:00~18:00,假日半小時計費,假日大車費率:10,假日小車費率:10,假日收費時段:08:00~18:00","hashCode":"15385798"},{"_id":97,"rd_name":"自強北路","rd_begin":"萬壽路二段","rd_end":"光峰路","rd_count":23,"use_cnt":"1","last_time":"2020/4/10 下午 05:56:00","tp_name":" 平日半小時計費,平日大車費率:10,平日小車費率:10,平日收費時段:08:00~18:00,假日半小時計費,假日大車費率:00,假日小車費率:0,假日收費時段:08:00~18:00","hashCode":"1276777977"},{"_id":98,"rd_name":"南崁路一","rd_begin":"立德街","rd_end":"南上路","rd_count":36,"use_cnt":"7","last_time":"2020/4/10 下午 08:45:00","tp_name":" 平日半小時計費,平日大車費率:15,平日小車費率:15,平日收費時段:07:00~20:00,假日半小時計費,假日大車費率:15,假日小車費率:15,假日收費時段:07:00~20:00","hashCode":"828044221"},{"_id":99,"rd_name":"南崁路二","rd_begin":"南上路","rd_end":"南華一街","rd_count":17,"use_cnt":"9","last_time":"2020/4/10 下午 08:45:00","tp_name":" 平日半小時計費,平日大車費率:15,平日小車費率:15,平日收費時段:07:00~20:00,假日無計費,假日大車費率:0,假日小車費率:0,假日收費時段:00:00~00:00","hashCode":"1599944511"},{"_id":100,"rd_name":"新南路一段","rd_begin":"南崁路","rd_end":"南華一街","rd_count":42,"use_cnt":"31","last_time":"2020/4/10 下午 08:45:00","tp_name":" 平日半小時計費,平日大車費率:15,平日小車費率:15,平日收費時段:07:00~20:00,假日半小時計費,假日大車費率:15,假日小車費率:15,假日收費時段:07:00~20:00","hashCode":"155649254"}],"offset":0,"total":329,"limit":100}}